LICENSE
MANIFEST.in
README.rst
setup.py
pilo/__init__.py
pilo/context.py
pilo/fields.py
pilo.egg-info/PKG-INFO
pilo.egg-info/SOURCES.txt
pilo.egg-info/dependency_links.txt
pilo.egg-info/requires.txt
pilo.egg-info/top_level.txt
pilo/source/__init__.py
pilo/source/configparser.py
pilo/source/default.py
pilo/source/json.py
pilo/source/mount.py
pilo/source/union.py