Metadata-Version: 1.1
Name: pilo
Version: 0.5.1
Summary: Yet another form parser.
Home-page: https://github.com/bninja/pilo/
Author: egon
Author-email: egon@gb.com
License: Copyright (c) 2014 terrans.
